{
  "title": "Implementatiemodel VKBO - Onderneming",
  "category": "https://data.vlaanderen.be/id/concept/StandaardType/Implementatiemodel",
  "usage": "https://data.vlaanderen.be/id/concept/StandaardGebruik/Aanbevolen",
  "status": "https://data.vlaanderen.be/id/concept/StandaardStatus/ZonderStatus",
  "descriptionFileName": "impl-vkbo-onderneming.md",
  "responsibleOrganisation": [
    {
      "name": "Agentschap Digitaal Vlaanderen",
      "resourceReference": "https://data.vlaanderen.be/id/organisatie/OVO002949"
    }
  ],
  "publicationDate": "2026-06-11",
  "specificationDocuments": [
    {
      "name": "Implementatiemodel VKBO - Onderneming",
      "resourceReference": "https://implementatie.data.vlaanderen.be/doc/implementatiemodel/vkbo/onderneming"
    }
  ],
  "documentation": [],
  "reports": [
  ],
  "charter": {
  },
  "presentations": [
  ],
  "implementations": [
    {
      "name": "Subjectpages Onderneming",
      "resourceReference": "https://data.vlaanderen.be/id/onderneming/"
    },
    {
      "name": "Subjectpages Vestiging",
      "resourceReference": "https://data.vlaanderen.be/id/vestiging/"
    }
  ],
  "relevantStandards": [
    {
      "name": "Vocabularium VKBO-Onderneming",
      "resourceReference": "https://implementatie.data.vlaanderen.be/ns/vkbo/onderneming#"
    },
    {
      "name": "Applicatieprofiel OSLO Organisatie",
      "resourceReference": "https://data.vlaanderen.be/doc/applicatieprofiel/organisatie-basis"
    },
    {
      "name": "Vocabularium OSLO Organisatie",
      "resourceReference": "https://data.vlaanderen.be/ns/organisatie#"
    },
    {
      "name": "W3C The Organization Ontology",
      "resourceReference": "https://www.w3.org/TR/vocab-org/"
    },
     {
      "name": "SEMIC Core Public Organisation Vocabulary",
      "resourceReference": "https://semiceu.github.io/CPOV/releases/2.1.2/"
    },
     {
      "name": "SEMIC Core Business Vocabulary",
      "resourceReference": "https://semiceu.github.io/Core-Business-Vocabulary/releases/2.3.0/"
    },
  ],
  "dataExamples": [
  ],
  "dateOfRegistration": "2026-04-21",
  "dateOfAcknowledgementByWorkingGroup": "n.v.t.",
  "dateOfAcknowledgementBySteeringCommittee": "n.v.t.",
  "repository": "OSLOthema-organisatie",
  "datePublicReviewStart": "n.v.t.",
  "endOfPublicationDate": "n.v.t.",
  "domain": "https://data.vlaanderen.be/id/concept/Domein/Economie"
}
